spots/__init__.py
spots/staypoint.py
spots/utils.py
spots-1.0.4.dist-info/METADATA
spots-1.0.4.dist-info/RECORD
spots-1.0.4.dist-info/WHEEL
spots-1.0.4.dist-info/top_level.txt
