Metadata-Version: 2.1
Name: spots
Version: 1.0.4
Summary: Google Location History utilities
Home-page: UNKNOWN
Author: Lucas Cardozo
Author-email: lucasecardozo@gmail.com
License: UNKNOWN
Platform: UNKNOWN
Requires-Dist: scikit-learn
Requires-Dist: pandas
Requires-Dist: numba
